pangeamt_toolkit/__init__.py
pangeamt_toolkit/pangeanmt/__init__.py
pangeamt_toolkit/pangeanmt/attention_matrix.py
pangeamt_toolkit/pangeanmt/onmtx_translation.py
pangeamt_toolkit/pangeanmt/onmtx_translator.py
pangeamt_toolkit/pangeanmt/pangeanmt.py
pangeamt_toolkit/pangeanmt/pangeanmt_server.py
pangeamt_toolkit/pangeanmt/translation.py
pangeamt_toolkit/pangeanmt/extended_model/__init__.py
pangeamt_toolkit/pangeanmt/extended_model/config.py
pangeamt_toolkit/pangeanmt/extended_model/extended_model.py
pangeamt_toolkit/pangeanmt/request_handler/__init__.py
pangeamt_toolkit/pangeanmt/request_handler/ready.py
pangeamt_toolkit/pangeanmt/request_handler/save.py
pangeamt_toolkit/pangeanmt/request_handler/train.py
pangeamt_toolkit/pangeanmt/request_handler/translate.py
pangeamt_toolkit/processors/__init__.py
pangeamt_toolkit/processors/bpe_processor.py
pangeamt_toolkit/processors/chinese_numbers_processor.py
pangeamt_toolkit/processors/general_tokenizer_processor.py
pangeamt_toolkit/processors/japanese_normalizer_processor.py
pangeamt_toolkit/processors/jieba_tokenizer_processor.py
pangeamt_toolkit/processors/mecab_tokenizer_processor.py
pangeamt_toolkit/processors/moses_normalizer_processor.py
pangeamt_toolkit/processors/moses_tokenizer_processor.py
pangeamt_toolkit/processors/moses_truecasing_processor.py
pangeamt_toolkit/processors/placeholder_processor.py
pangeamt_toolkit/processors/processor_base.py
pangeamt_toolkit/processors/processors_pipeline.py
pangeamt_toolkit/processors/punct_processor.py
pangeamt_toolkit/seg/__init__.py
pangeamt_toolkit/seg/seg.py
pangeamt_toolkit/seg/seg_case.py
pangeamt_toolkit-3.57.0.data/scripts/auto_tmx2bilingual.py
pangeamt_toolkit-3.57.0.data/scripts/get_training_steps.py
pangeamt_toolkit-3.57.0.data/scripts/pangeamt_build_server.py
pangeamt_toolkit-3.57.0.data/scripts/pangeamt_file_postprocess.py
pangeamt_toolkit-3.57.0.data/scripts/pangeamt_file_preprocess.py
pangeamt_toolkit-3.57.0.data/scripts/pangeamt_files_preprocess.py
pangeamt_toolkit-3.57.0.dist-info/LICENSE.txt
pangeamt_toolkit-3.57.0.dist-info/METADATA
pangeamt_toolkit-3.57.0.dist-info/WHEEL
pangeamt_toolkit-3.57.0.dist-info/top_level.txt
pangeamt_toolkit-3.57.0.dist-info/RECORD
